Examples/5_test_api_finam_v1.py
Examples/Accounts.py
Examples/Bars.py
Examples/Connect.py
Examples/FinamPy.py
Examples/Stream.py
Examples/Ticker.py
Examples/Transactions.py
Examples/__init__.py
FinamPy-0.0.2.dist-info/METADATA
FinamPy-0.0.2.dist-info/WHEEL
FinamPy-0.0.2.dist-info/top_level.txt
FinamPy-0.0.2.dist-info/RECORD
